exl2conv/__init__.py
exl2conv/architecture.py
exl2conv/attn.py
exl2conv/cache.py
exl2conv/compat.py
exl2conv/config.py
exl2conv/embedding.py
exl2conv/ext.py
exl2conv/fasttensors.py
exl2conv/headnorm.py
exl2conv/layernorm.py
exl2conv/linear.py
exl2conv/lora.py
exl2conv/mlp.py
exl2conv/model.py
exl2conv/model_init.py
exl2conv/module.py
exl2conv/moe_mlp.py
exl2conv/parallel_decoder.py
exl2conv/pos_embedding.py
exl2conv/rmsnorm.py
exl2conv/tokenizer.py
exl2conv/util.py
exl2conv/version.py
exl2conv/conversion/adaptivegptq.py
exl2conv/conversion/compile.py
exl2conv/conversion/convert.py
exl2conv/conversion/measure.py
exl2conv/conversion/optimize.py
exl2conv/conversion/qparams.py
exl2conv/conversion/quantize.py
exl2conv/conversion/tokenize.py
exl2conv/conversion/standard_cal_data/c4.utf8
exl2conv/conversion/standard_cal_data/code.utf8
exl2conv/conversion/standard_cal_data/multilingual.utf8
exl2conv/conversion/standard_cal_data/technical.utf8
exl2conv/conversion/standard_cal_data/tiny.utf8
exl2conv/conversion/standard_cal_data/wiki.utf8
exl2conv/exl2conv_ext/config.h
exl2conv/exl2conv_ext/ext_bindings.cpp
exl2conv/exl2conv_ext/ext_cache.cpp
exl2conv/exl2conv_ext/ext_cache.h
exl2conv/exl2conv_ext/ext_gemm.cpp
exl2conv/exl2conv_ext/ext_gemm.h
exl2conv/exl2conv_ext/ext_hadamard.cpp
exl2conv/exl2conv_ext/ext_hadamard.h
exl2conv/exl2conv_ext/ext_norm.cpp
exl2conv/exl2conv_ext/ext_norm.h
exl2conv/exl2conv_ext/ext_qattn.cpp
exl2conv/exl2conv_ext/ext_qattn.h
exl2conv/exl2conv_ext/ext_qmatrix.cpp
exl2conv/exl2conv_ext/ext_qmatrix.h
exl2conv/exl2conv_ext/ext_qmlp.cpp
exl2conv/exl2conv_ext/ext_qmlp.h
exl2conv/exl2conv_ext/ext_quant.cpp
exl2conv/exl2conv_ext/ext_quant.h
exl2conv/exl2conv_ext/ext_rope.cpp
exl2conv/exl2conv_ext/ext_rope.h
exl2conv/exl2conv_ext/ext_safetensors.cpp
exl2conv/exl2conv_ext/ext_safetensors.h
exl2conv/exl2conv_ext/ext_sampling.cpp
exl2conv/exl2conv_ext/ext_sampling.h
exl2conv/exl2conv_ext/cpp/avx2_target.h
exl2conv/exl2conv_ext/cpp/avx_mathfun.h
exl2conv-0.0.21.dist-info/LICENSE
exl2conv-0.0.21.dist-info/METADATA
exl2conv-0.0.21.dist-info/WHEEL
exl2conv-0.0.21.dist-info/top_level.txt
exl2conv-0.0.21.dist-info/RECORD
