Metadata-Version: 2.1
Name: exl2conv
Version: 0.0.21
Home-page: https://github.com/xhedit/exl2conv
Author: xhedit
License: MIT
License-File: LICENSE
Requires-Dist: pandas
Requires-Dist: ninja
Requires-Dist: fastparquet
Requires-Dist: torch >=2.2.0
Requires-Dist: safetensors >=0.3.2
Requires-Dist: sentencepiece >=0.1.97
Requires-Dist: pygments
Requires-Dist: websockets
Requires-Dist: regex
Requires-Dist: numpy
